<?xml version="1.0" encoding="utf-8" ?>
<resources>
 <stringres id="genericlogin/window1.title">
  <xmbtext>Inloggning</xmbtext>
 </stringres>
 <stringres id="genericlogin/emaillabel.title">
  <xmbtext>E-post:</xmbtext>
 </stringres>
 <stringres id="genericlogin/createlink.title">
  <xmbtext>Skapa ett konto...</xmbtext>
 </stringres>
 <stringres id="genericlogin/createlink.url">
  <xmbtext>http://www.google.com</xmbtext>
 </stringres>
 <stringres id="genericlogin/labelgroup7.title">
  <xmbtext>Lösenord:</xmbtext>
 </stringres>
 <stringres id="genericlogin/forgotlink.title">
  <xmbtext>Har du glömt ditt lösenord?</xmbtext>
 </stringres>
 <stringres id="genericlogin/forgotlink.url">
  <xmbtext>http://www.google.com</xmbtext>
 </stringres>
 <stringres id="genericlogin/savepassword.title">
  <xmbtext>Spara lösenord</xmbtext>
 </stringres>
 <stringres id="genericlogin/label14.title">
  <xmbtext>Säker inloggning med SSL</xmbtext>
 </stringres>
 <stringres id="genericlogin/accept.title">
  <xmbtext>Logga in</xmbtext>
 </stringres>
 <stringres id="genericlogin/button17.title">
  <xmbtext>Avbryt</xmbtext>
 </stringres>
</resources>
