<?xml version="1.0" encoding="utf-8" ?>
<resources>
 <stringres id="gpuploader_file_errors/file_errors.title">
  <xmbtext>Zálohovanie Fotiek Google</xmbtext>
 </stringres>
 <stringres id="gpuploader_file_errors/error_label.title">
  <xmbtext>Tieto súbory sa nepodarilo zálohovať:</xmbtext>
 </stringres>
 <stringres id="gpuploader_file_errors/namecolumn.title">
  <xmbtext>Názov</xmbtext>
 </stringres>
 <stringres id="gpuploader_file_errors/accept.title">
  <xmbtext>Skúsiť znova</xmbtext>
 </stringres>
 <stringres id="gpuploader_file_errors/cancel.title">
  <xmbtext>Zrušiť</xmbtext>
 </stringres>
</resources>
