<?xml version="1.0" encoding="utf-8" ?>
<resources>
 <stringres id="export/window1.title">
  <xmbtext>In Ordner exportieren</xmbtext>
 </stringres>
 <stringres id="export/labelgroup2.title">
  <xmbtext>Speicherort für Export:</xmbtext>
 </stringres>
 <stringres id="export/changeloc.title">
  <xmbtext>Durchsuchen…</xmbtext>
 </stringres>
 <stringres id="export/labelgroup6.title">
  <xmbtext>Name des exportierten Ordners:</xmbtext>
 </stringres>
 <stringres id="export/addnumbers.title">
  <xmbtext>Fügen Sie Zahlen zu Dateinamen hinzu, um den Überblick zu behalten.</xmbtext>
 </stringres>
 <stringres id="export/labelgroup9.title">
  <xmbtext>Bildgröße:</xmbtext>
 </stringres>
 <stringres id="export/radio11.title">
  <xmbtext>Originalgröße verwenden</xmbtext>
 </stringres>
 <stringres id="export/radio12.title">
  <xmbtext>Größe ändern in:</xmbtext>
 </stringres>
 <stringres id="export/bind17.list">
  <xmbtext>320|480|640|800|1024|1200|1600</xmbtext>
 </stringres>
 <stringres id="export/label18.title">
  <xmbtext>Pixel</xmbtext>
 </stringres>
 <stringres id="export/labelgroup20.title">
  <xmbtext>Bildqualität:</xmbtext>
 </stringres>
 <stringres id="export/item23.title">
  <xmbtext>Automatisch</xmbtext>
 </stringres>
 <stringres id="export/item24.title">
  <xmbtext>Normal</xmbtext>
 </stringres>
 <stringres id="export/item25.title">
  <xmbtext>Maximum</xmbtext>
 </stringres>
 <stringres id="export/item26.title">
  <xmbtext>Minimum</xmbtext>
 </stringres>
 <stringres id="export/item27.title">
  <xmbtext>Benutzerdefiniert</xmbtext>
 </stringres>
 <stringres id="export/label30.title">
  <xmbtext>Ursprüngliche Bildqualität wird beibehalten</xmbtext>
 </stringres>
 <stringres id="export/label31.title">
  <xmbtext>Guter Kompromiss zwischen Qualität und Größe</xmbtext>
 </stringres>
 <stringres id="export/label32.title">
  <xmbtext>Sehr große Dateigröße, feine Details bleiben erhalten</xmbtext>
 </stringres>
 <stringres id="export/label33.title">
  <xmbtext>Kleinste Dateigröße, etwas Qualitätsverlust</xmbtext>
 </stringres>
 <stringres id="export/labelgroup35.title">
  <xmbtext>Filme exportieren mit:</xmbtext>
 </stringres>
 <stringres id="export/radio37.title">
  <xmbtext>Erster Frame</xmbtext>
 </stringres>
 <stringres id="export/radio38.title">
  <xmbtext>Ganzer Film (keine Größenänderung)</xmbtext>
 </stringres>
 <stringres id="export/labelgroup39.title">
  <xmbtext>Wasserzeichen:</xmbtext>
 </stringres>
 <stringres id="export/usewatermark.title">
  <xmbtext>Wasserzeichen hinzufügen</xmbtext>
 </stringres>
 <stringres id="export/label44.title">
  <xmbtext>Versehen Sie Fotos mit Ihrem Namen, einer Web-Domain oder einem Urheberrechtshinweis.</xmbtext>
 </stringres>
 <stringres id="export/export.title">
  <xmbtext>Exportieren</xmbtext>
 </stringres>
 <stringres id="export/button47.title">
  <xmbtext>Abbrechen</xmbtext>
 </stringres>
</resources>
