<?xml version="1.0" encoding="utf-8" ?>
<tooltips>
 <action type="Text" target="upload/public_label" xmbdesc="Text(upload/public_label)">
  <xmbtext>웹에 공개</xmbtext>
 </action>
 <action type="Text" target="upload/private_label" xmbdesc="Text(upload/private_label)">
  <xmbtext>링크가 있는 모든 사용자에게 공개</xmbtext>
 </action>
 <action type="Text" target="upload/public_description1" xmbdesc="Text(upload/public_description1)">
  <xmbtext>%s의 모든 사용자가 볼 수 있는 앨범입니다.</xmbtext>
 </action>
 <action type="Text" target="upload/private_description1" xmbdesc="Text(upload/private_description1)">
  <xmbtext>선택한 사용자와 공유</xmbtext>
 </action>
 <action type="Text" target="upload/uploadinfo" xmbdesc="Text(upload/uploadinfo)">
  <xmbtext>온라인 상태 확인 중...</xmbtext>
 </action>
 <action type="Text" target="upload/webalbumstext" xmbdesc="Text(upload/webalbumstext)">
  <xmbtext>웹앨범 목록 업데이트 중...</xmbtext>
 </action>
 <action type="Text" target="upload/upload_label" xmbdesc="Text(upload/upload_label)">
  <xmbtext>앨범에 업로드:</xmbtext>
 </action>
 <action type="Text" target="upload/uploadsize_label" xmbdesc="Text(upload/uploadsize_label)">
  <xmbtext>업로드할 크기</xmbtext>
 </action>
 <action type="Text" target="upload/privacy_label" xmbdesc="Text(upload/privacy_label)">
  <xmbtext>개인정보</xmbtext>
 </action>
 <action type="Text" target="upload/require_login_text" xmbdesc="Text(upload/require_login_text)">
  <xmbtext>비공개</xmbtext>
 </action>
 <action type="Label" target="upload/newalbum2" xmbdesc="Label(upload/newalbum2)">
  <xmbtext>새 앨범</xmbtext>
 </action>
 <action type="Text" target="upload/titlelabel" xmbdesc="Text(upload/titlelabel)">
  <xmbtext>앨범 제목</xmbtext>
 </action>
 <action type="Text" target="upload/desclabel" xmbdesc="Text(upload/desclabel)">
  <xmbtext>설명</xmbtext>
 </action>
 <action type="Text" target="upload/choose_contact_label" xmbdesc="Text(upload/choose_contact_label)">
  <xmbtext>연락처 선택:</xmbtext>
 </action>
 <action type="Text" target="upload/contact_album_list_label" xmbdesc="Text(upload/contact_album_list_label)">
  <xmbtext>참여할 수 있는 연락처 앨범:</xmbtext>
 </action>
 <action type="Label" target="upload/upgrade" xmbdesc="Label(upload/upgrade)">
  <xmbtext>업그레이드</xmbtext>
 </action>
 <action type="Label" target="upload/ok" xmbdesc="Label(upload/ok)">
  <xmbtext>업로드</xmbtext>
 </action>
 <action type="Label" target="upload/cancel" xmbdesc="Label(upload/cancel)">
  <xmbtext>취소</xmbtext>
 </action>
 <action type="Label" target="upload/storagetext" xmbdesc="Label(upload/storagetext)">
  <xmbtext>자세히 알아보기...</xmbtext>
 </action>
 <action type="Text" target="upload/account_title" xmbdesc="Text(upload/account_title)">
  <xmbtext>계정:</xmbtext>
 </action>
 <action type="Text" target="upload/upsell_text" xmbdesc="Text(upload/upsell_text)">
  <xmbtext>추가 저장용량을 이용하여 사진을 안전하게 백업할 수 있습니다.</xmbtext>
 </action>
 <action type="Label" target="upload/collab_label" xmbdesc="Label(upload/collab_label)">
  <xmbtext>내 앨범에 제공 허용</xmbtext>
 </action>
 <action type="Label" target="upload/sharing_label" xmbdesc="Label(upload/sharing_label)">
  <xmbtext>공유:</xmbtext>
 </action>
</tooltips>
