<?xml version="1.0" encoding="utf-8" ?>
<resources>
 <stringres id="gpuploader_main/window.title">
  <xmbtext>Device and Auto-backup Status</xmbtext>
 </stringres>
 <stringres id="gpuploader_main/show_options.title">
  <xmbtext>Options...</xmbtext>
 </stringres>
 <stringres id="gpuploader_main/problem_retry.title">
  <xmbtext>Retry</xmbtext>
 </stringres>
 <stringres id="gpuploader_main/problem_skip.title">
  <xmbtext>Skip</xmbtext>
 </stringres>
 <stringres id="gpuploader_main/device_title.title">
  <xmbtext>Devices</xmbtext>
 </stringres>
 <stringres id="gpuploader_main/namecolumn.title">
  <xmbtext>Name</xmbtext>
 </stringres>
 <stringres id="gpuploader_main/statuscolumn.title">
  <xmbtext>Status</xmbtext>
 </stringres>
 <stringres id="gpuploader_main/import_from_device.title">
  <xmbtext>Import</xmbtext>
 </stringres>
 <stringres id="gpuploader_main/exit.title">
  <xmbtext>Exit</xmbtext>
 </stringres>
</resources>
