<?xml version="1.0" encoding="utf-8" ?>
<resources>
 <stringres id="gpuploader_quota_error_estimate/quota_error2.title">
  <xmbtext>Google+ Auto Back-up</xmbtext>
 </stringres>
 <stringres id="gpuploader_quota_error_estimate/error_label.title">
  <xmbtext>Out of storage</xmbtext>
 </stringres>
 <stringres id="gpuploader_quota_error_estimate/estimate_error_text.title">
  <xmbtext>You&#039;ve selected folders that contain more space than your remaining Google Drive storage. You can either buy more storage space or back up unlimited photos and videos at the standard size for free.</xmbtext>
 </stringres>
 <stringres id="gpuploader_quota_error_estimate/error_note.title">
  <xmbtext>If you&#039;ve just purchased storage, it may take a few minutes for the changes to take effect.</xmbtext>
 </stringres>
 <stringres id="gpuploader_quota_error_estimate/add_more_storage.title">
  <xmbtext>Get more storage...</xmbtext>
 </stringres>
 <stringres id="gpuploader_quota_error_estimate/accept.title">
  <xmbtext>Switch to standard size</xmbtext>
 </stringres>
</resources>
