<?xml version="1.0" encoding="utf-8" ?>
<tooltips>
 <action type="Label" target="capturemoviepanelpopup/done" xmbdesc="Label(capturemoviepanelpopup/done)">
  <xmbtext>Bitti</xmbtext>
 </action>
 <action type="Label" target="capturemoviepanelpopup/capture" xmbdesc="Label(capturemoviepanelpopup/capture)">
  <xmbtext>Kayıt</xmbtext>
 </action>
 <action type="Label" target="capturemoviepanelpopup/stop" xmbdesc="Label(capturemoviepanelpopup/stop)">
  <xmbtext>Durdur</xmbtext>
 </action>
 <action type="Label" target="capturemoviepanelpopup/live_video" xmbdesc="Label(capturemoviepanelpopup/live_video)">
  <xmbtext>Kamera</xmbtext>
 </action>
 <action type="Label" target="capturemoviepanelpopup/camchange" xmbdesc="Label(capturemoviepanelpopup/camchange)">
  <xmbtext>Ayarlar</xmbtext>
 </action>
 <action type="Tooltip" target="capturemoviepanelpopup/capture" xmbdesc="Tooltip(capturemoviepanelpopup/capture)">
  <xmbtext>Kamera kaydını başlat</xmbtext>
 </action>
 <action type="Tooltip" target="capturemoviepanelpopup/stop" xmbdesc="Tooltip(capturemoviepanelpopup/stop)">
  <xmbtext>Kamera kaydını durdur</xmbtext>
 </action>
 <action type="Tooltip" target="capturemoviepanelpopup/live_video" xmbdesc="Tooltip(capturemoviepanelpopup/live_video)">
  <xmbtext>Kamerayla canlı videolar kaydedin</xmbtext>
 </action>
 <action type="Tooltip" target="capturemoviepanelpopup/camchange" xmbdesc="Tooltip(capturemoviepanelpopup/camchange)">
  <xmbtext>Fotoğraf makinesi ayarlarını değiştir</xmbtext>
 </action>
 <action type="Label" target="capturemoviepanelpopup/settings_cancel" xmbdesc="Label(capturemoviepanelpopup/settings_cancel)">
  <xmbtext>İptal</xmbtext>
 </action>
 <action type="Label" target="capturemoviepanelpopup/settings_apply" xmbdesc="Label(capturemoviepanelpopup/settings_apply)">
  <xmbtext>Uygula</xmbtext>
 </action>
 <action type="Label" target="capturemoviepanelpopup/video_label" xmbdesc="Label(capturemoviepanelpopup/video_label)">
  <xmbtext>Video</xmbtext>
 </action>
 <action type="Label" target="capturemoviepanelpopup/size_label" xmbdesc="Label(capturemoviepanelpopup/size_label)">
  <xmbtext>Boyut</xmbtext>
 </action>
 <action type="Label" target="capturemoviepanelpopup/audio_label" xmbdesc="Label(capturemoviepanelpopup/audio_label)">
  <xmbtext>Ses</xmbtext>
 </action>
</tooltips>
