<?xml version="1.0" encoding="utf-8" ?>
<resources>
 <stringres id="gpuploader_storage_notify/window.title">
  <xmbtext>Резервне копије Google слика</xmbtext>
 </stringres>
 <stringres id="gpuploader_storage_notify/notify_header.title">
  <xmbtext>Нове Резервне копије Google слика</xmbtext>
 </stringres>
 <stringres id="gpuploader_storage_notify/notify_text.title">
  <xmbtext>Опције складишног простора за слике и видео су се управо много побољшале.</xmbtext>
 </stringres>
 <stringres id="gpuploader_storage_notify/notify_learnmore.title">
  <xmbtext>Сазнајте више</xmbtext>
 </stringres>
 <stringres id="gpuploader_storage_notify/notify_learnmore.url">
  <xmbtext>https://support.google.com/plus/answer/1647509#cost</xmbtext>
 </stringres>
 <stringres id="gpuploader_storage_notify/free_size.title">
  <xmbtext>Висок квалитет (бесплатан неограничен складишни простор)</xmbtext>
 </stringres>
 <stringres id="gpuploader_storage_notify/free_size_desc.title">
  <xmbtext>Одличан визуелни квалитет уз смањену величину датотеке</xmbtext>
 </stringres>
 <stringres id="gpuploader_storage_notify/full_size.title">
  <xmbtext>Оригинал (Проверава се капацитет преосталог складишног простора...)</xmbtext>
 </stringres>
 <stringres id="gpuploader_storage_notify/full_size_desc.title">
  <xmbtext>Пуна резолуција која улази у квоту</xmbtext>
 </stringres>
 <stringres id="gpuploader_storage_notify/notify_extra.title">
  <xmbtext>Прегледајте оно што сте отпремили и погледајте све нове функције Google слика на photos.google.com</xmbtext>
 </stringres>
 <stringres id="gpuploader_storage_notify/okbutton.title">
  <xmbtext>Потврди</xmbtext>
 </stringres>
</resources>
