<?xml version="1.0" encoding="utf-8" ?>
<tooltips>
 <action type="Label" target="login/signin" xmbdesc="Label(login/signin)">
  <xmbtext>Prijava</xmbtext>
 </action>
 <action type="Label" target="login/cancel" xmbdesc="Label(login/cancel)">
  <xmbtext>Prekliči</xmbtext>
 </action>
 <action type="Label" target="login/rememberpass" xmbdesc="Label(login/rememberpass)">
  <xmbtext>Zapomni si me v tem računalniku</xmbtext>
 </action>
 <action type="Label" target="login/usernametxt" xmbdesc="Label(login/usernametxt)">
  <xmbtext>Uporabniško ime:</xmbtext>
 </action>
 <action type="Label" target="login/passwordtxt" xmbdesc="Label(login/passwordtxt)">
  <xmbtext>Geslo:</xmbtext>
 </action>
 <action type="Label" target="login/picasaintro" xmbdesc="Label(login/picasaintro)">
  <xmbtext>Če želite poslati fotografije s Picaso, uporabite svoje uporabniško ime storitve Hello.</xmbtext>
 </action>
 <action type="Label" target="login/plogin" xmbdesc="Label(login/plogin)">
  <xmbtext>Prijava</xmbtext>
 </action>
 <action type="Label" target="login/pcancel" xmbdesc="Label(login/pcancel)">
  <xmbtext>Prekliči</xmbtext>
 </action>
 <action type="Label" target="login/forgotpw" xmbdesc="Label(login/forgotpw)">
  <xmbtext>Ste pozabili geslo?</xmbtext>
 </action>
 <action type="Label" target="login/gphotos_logotext" xmbdesc="Label(login/gphotos_logotext)">
  <xmbtext>Spletni albumi</xmbtext>
 </action>
 <action type="Label" target="login/gphotosintro" xmbdesc="Label(login/gphotosintro)">
  <xmbtext>Prijava v spletne albume</xmbtext>
 </action>
 <action type="Label" target="login/gphotostext" xmbdesc="Label(login/gphotostext)">
  <xmbtext>Spletni albumi omogočajo skupno rabo albumov v spletu s prijatelji in družinskimi člani ali ustvarjanje javnih albumov, ki si jih lahko delite z vsemi ljudmi. So brezplačni in preprosti za uporabo.</xmbtext>
 </action>
 <action type="Label" target="login/gphotossignup" xmbdesc="Label(login/gphotossignup)">
  <xmbtext>Google Račun je veljaven, vendar še niste ustvarili računa za spletne albume.</xmbtext>
 </action>
 <action type="Label" target="login/gphotoslink" xmbdesc="Label(login/gphotoslink)">
  <xmbtext>Kliknite tukaj, če želite izvedeti več o tem.</xmbtext>
 </action>
 <action type="Label" target="login/webalbum_activate" xmbdesc="Label(login/webalbum_activate)">
  <xmbtext>Aktiviraj spletne albume ...</xmbtext>
 </action>
 <action type="Label" target="login/webalbum_signup" xmbdesc="Label(login/webalbum_signup)">
  <xmbtext>Prijavite se za spletne albume</xmbtext>
 </action>
 <action type="Label" target="login/gvideointro" xmbdesc="Label(login/gvideointro)">
  <xmbtext>Naložite svoje filme iz Picase v Google Video.</xmbtext>
 </action>
 <action type="Label" target="login/gvideotext" xmbdesc="Label(login/gvideotext)">
  <xmbtext>Če želite začeti nalaganje, se prijavite spodaj.</xmbtext>
 </action>
 <action type="Label" target="login/gvideolink" xmbdesc="Label(login/gvideolink)">
  <xmbtext>Če želite izvedeti več, kliknite tukaj.</xmbtext>
 </action>
 <action type="Label" target="login/gvideosignup2" xmbdesc="Label(login/gvideosignup2)">
  <xmbtext>Ustvari račun</xmbtext>
 </action>
 <action type="Label" target="login/gmailintro" xmbdesc="Label(login/gmailintro)">
  <xmbtext>Pošljite fotografije iz Picase prek Google Računa.</xmbtext>
 </action>
 <action type="Label" target="login/gpoint1" xmbdesc="Label(login/gpoint1)">
  <xmbtext>Pošiljanje slik se v celoti izvaja brez brskalnika</xmbtext>
 </action>
 <action type="Label" target="login/gpoint2" xmbdesc="Label(login/gpoint2)">
  <xmbtext>Pošiljanje do 10 MB fotografij</xmbtext>
 </action>
 <action type="Label" target="login/gpoint4" xmbdesc="Label(login/gpoint4)">
  <xmbtext>Ali želite Gmail? Pridobite brezplačen račun, z več kot 6,5 GB pomnilnika (in še raste).</xmbtext>
 </action>
 <action type="WebTarget" target="login/gpoint4" xmbdesc="WebTarget(login/gpoint4)">
  <xmbtext>http://mail.google.com</xmbtext>
 </action>
 <action type="Label" target="login/gpoint3" xmbdesc="Label(login/gpoint3)">
  <xmbtext>Predogled fotografij pred pošiljanjem</xmbtext>
 </action>
 <action type="Label" target="login/error" xmbdesc="Label(login/error)">
  <xmbtext>Uporabniško ime ali geslo ni pravilno. Poskusite ponovno.</xmbtext>
 </action>
 <action type="Label" target="login/captchaerror" xmbdesc="Label(login/captchaerror)">
  <xmbtext>Uporabniško ime in geslo se ne ujemata. </xmbtext>
 </action>
 <action type="Label" target="login/captchaerror2" xmbdesc="Label(login/captchaerror2)">
  <xmbtext>V zgornje polje vnesite pravilno geslo, nato pa vnesite znake s spodnje slike (pri tem pazite na velike in male črke)</xmbtext>
 </action>
 <action type="Label" target="login/rememberpasscaptcha" xmbdesc="Label(login/rememberpasscaptcha)">
  <xmbtext>Zapomni si me v tem računalniku</xmbtext>
 </action>
 <action type="Label" target="login/signincaptcha" xmbdesc="Label(login/signincaptcha)">
  <xmbtext>Prijava</xmbtext>
 </action>
 <action type="Label" target="login/cancelcaptcha" xmbdesc="Label(login/cancelcaptcha)">
  <xmbtext>Prekliči</xmbtext>
 </action>
</tooltips>
