<?xml version="1.0" encoding="utf-8" ?>
<resources>
 <stringres id="gpuploader_download/window.title">
  <xmbtext>Google Foto&#039;s Back-up</xmbtext>
 </stringres>
 <stringres id="gpuploader_download/device_name.title">
  <xmbtext>Een back-up maken van foto&#039;s van %1$s?</xmbtext>
 </stringres>
 <stringres id="gpuploader_download/action_prompt.title">
  <xmbtext>Foto&#039;s en video&#039;s van dit apparaat opslaan in Google Foto&#039;s</xmbtext>
 </stringres>
 <stringres id="gpuploader_download/never_btn.title">
  <xmbtext>Nooit</xmbtext>
 </stringres>
 <stringres id="gpuploader_download/once_btn.title">
  <xmbtext>Eén keer</xmbtext>
 </stringres>
 <stringres id="gpuploader_download/always_btn.title">
  <xmbtext>Altijd</xmbtext>
 </stringres>
</resources>
