<?xml version="1.0" encoding="utf-8" ?>
<resources>
 <stringres id="gpuploader_onboard/onboard_window.title">
  <xmbtext>Google Foto&#039;s Back-up</xmbtext>
 </stringres>
 <stringres id="gpuploader_onboard/select_text_1.title">
  <xmbtext>Back-upbronnen kiezen</xmbtext>
 </stringres>
 <stringres id="gpuploader_onboard/select_text_2.title">
  <xmbtext>Google Foto&#039;s maakt automatisch een back-up van foto&#039;s en video&#039;s uit geselecteerde bronnen in uw Foto&#039;s-bibliotheek.</xmbtext>
 </stringres>
 <stringres id="gpuploader_onboard/add_folder_btn.title">
  <xmbtext>Toevoegen…</xmbtext>
 </stringres>
 <stringres id="gpuploader_onboard/upload_size_label.title">
  <xmbtext>Fotoformaat</xmbtext>
 </stringres>
 <stringres id="gpuploader_onboard/free_size.title">
  <xmbtext>Hoge kwaliteit (gratis onbeperkte opslag)</xmbtext>
 </stringres>
 <stringres id="gpuploader_onboard/free_size_desc.title">
  <xmbtext>Prima beeldkwaliteit met een beperkte bestandsgrootte</xmbtext>
 </stringres>
 <stringres id="gpuploader_onboard/full_size.title">
  <xmbtext>Origineel (beperkt tot accountopslag)</xmbtext>
 </stringres>
 <stringres id="gpuploader_onboard/full_size_desc.title">
  <xmbtext>Volledige resolutie die meetelt voor uw quotum</xmbtext>
 </stringres>
 <stringres id="gpuploader_onboard/send_to_google.title">
  <xmbtext>Help Google Foto&#039;s verbeteren door anonieme gebruiksstatistieken te verzenden.</xmbtext>
 </stringres>
 <stringres id="gpuploader_onboard/more_storage.title">
  <xmbtext>Meer opslagruimte kopen...</xmbtext>
 </stringres>
 <stringres id="gpuploader_onboard/start_btn.title">
  <xmbtext>Back-up starten</xmbtext>
 </stringres>
</resources>
