<?xml version="1.0" encoding="utf-8" ?>
<resources>
 <stringres id="newbackupset/window1.title">
  <xmbtext>Novo conjunto de backups</xmbtext>
 </stringres>
 <stringres id="newbackupset/labelgroup2.title">
  <xmbtext>Nome:</xmbtext>
 </stringres>
 <stringres id="newbackupset/typegroup.title">
  <xmbtext>Tipo de backup:</xmbtext>
 </stringres>
 <stringres id="newbackupset/radio6.title">
  <xmbtext>Backup em CD ou DVD</xmbtext>
 </stringres>
 <stringres id="newbackupset/radio7.title">
  <xmbtext>Backup em outro disco (unidades externas e de rede)</xmbtext>
 </stringres>
 <stringres id="newbackupset/disk.title">
  <xmbtext>Escolher...</xmbtext>
 </stringres>
 <stringres id="newbackupset/labelgroup12.title">
  <xmbtext>Arquivos para fazer backup:</xmbtext>
 </stringres>
 <stringres id="newbackupset/radio14.title">
  <xmbtext>Todos os tipos de arquivo</xmbtext>
 </stringres>
 <stringres id="newbackupset/radio15.title">
  <xmbtext>Todas as imagens (excluir filmes)</xmbtext>
 </stringres>
 <stringres id="newbackupset/radio16.title">
  <xmbtext>Somente JPEGs com informações de câmera</xmbtext>
 </stringres>
 <stringres id="newbackupset/ok.title">
  <xmbtext>Criar</xmbtext>
 </stringres>
 <stringres id="newbackupset/button19.title">
  <xmbtext>Cancelar</xmbtext>
 </stringres>
</resources>
