<?xml version="1.0" encoding="utf-8" ?>
<resources>
 <stringres id="gpuploader_download/window.title">
  <xmbtext>Google Fotók Automatikus mentés</xmbtext>
 </stringres>
 <stringres id="gpuploader_download/device_name.title">
  <xmbtext>Szeretné automatikusan menteni a fotókat innen: %1$s?</xmbtext>
 </stringres>
 <stringres id="gpuploader_download/action_prompt.title">
  <xmbtext>Fotók és videók mentése erről az eszközről a Google Fotókba</xmbtext>
 </stringres>
 <stringres id="gpuploader_download/never_btn.title">
  <xmbtext>Soha</xmbtext>
 </stringres>
 <stringres id="gpuploader_download/once_btn.title">
  <xmbtext>Csak egyszer</xmbtext>
 </stringres>
 <stringres id="gpuploader_download/always_btn.title">
  <xmbtext>Mindig</xmbtext>
 </stringres>
</resources>
